tap_pypistats/__init__.py
tap_pypistats/tap.py
tap_pypistats-0.0.16.dist-info/METADATA
tap_pypistats-0.0.16.dist-info/WHEEL
tap_pypistats-0.0.16.dist-info/entry_points.txt
tap_pypistats-0.0.16.dist-info/licenses/LICENSE
tap_pypistats-0.0.16.dist-info/RECORD
