Metadata-Version: 2.4
Name: tap-pypistats
Version: 0.0.16
Summary: Singer tap for pypistats.org
Project-URL: Documentation, https://github.com/edgarrmondragon/tap-pypistats#readme
Project-URL: Homepage, https://github.com/edgarrmondragon/tap-pypistats
License-Expression: Apache-2.0
License-File: LICENSE
Keywords: meltano,pypistats,singer-io,singer-tap
Classifier: Programming Language :: Python :: 3 :: Only
Classifier: Programming Language :: Python :: 3.10
Classifier: Programming Language :: Python :: 3.11
Classifier: Programming Language :: Python :: 3.12
Classifier: Programming Language :: Python :: 3.13
Classifier: Programming Language :: Python :: 3.14
Classifier: Programming Language :: Python :: 3.15
Requires-Python: >=3.10
Requires-Dist: requests-cache~=1.2
Requires-Dist: requests~=2.32
Provides-Extra: pinned
Requires-Dist: attrs==25.4.0; extra == 'pinned'
Requires-Dist: cattrs==25.3.0; extra == 'pinned'
Requires-Dist: certifi==2026.1.4; extra == 'pinned'
Requires-Dist: charset-normalizer==3.4.4; extra == 'pinned'
Requires-Dist: exceptiongroup==1.3.1; (python_full_version < '3.11') and extra == 'pinned'
Requires-Dist: idna==3.11; extra == 'pinned'
Requires-Dist: platformdirs==4.5.1; extra == 'pinned'
Requires-Dist: requests-cache==1.3.0a1; extra == 'pinned'
Requires-Dist: requests==2.32.5; extra == 'pinned'
Requires-Dist: typing-extensions==4.15.0; extra == 'pinned'
Requires-Dist: typing-extensions==4.15.0; (python_full_version < '3.11' and python_full_version < '3.13') and extra == 'pinned'
Requires-Dist: url-normalize==2.2.1; extra == 'pinned'
Requires-Dist: urllib3==2.6.3; extra == 'pinned'
